MediaCapture/MediaCapture.py
MediaCapture/__init__.py
mediacapture-0.1.0.dist-info/licenses/LICENSE
mediacapture-0.1.0.dist-info/METADATA
mediacapture-0.1.0.dist-info/WHEEL
mediacapture-0.1.0.dist-info/top_level.txt
mediacapture-0.1.0.dist-info/RECORD
