Metadata-Version: 2.4
Name: MediaCapture
Version: 0.1.0
Summary: An easy way to capture and stream media from multiple cameras and from the screen
Author: Tristan McBride Sr.
Author-email: "Tristan McBride Sr." <142635792+TristanMcBrideSr@users.noreply.github.com>
Project-URL: Homepage, https://github.com/TristanMcBrideSr
Requires-Python: >=3.10
License-File: LICENSE
Requires-Dist: opencv-python
Requires-Dist: numpy
Requires-Dist: Pillow
Dynamic: author
Dynamic: license-file
